{
    "authorName": "pandur",
    "id": "02100bb5-fe07-4c1b-8792-67f9add7afff",
    "created": 1519999019701,
    "layout": {
        "portsIn": [
            {
                "type": "1",
                "name": "Calculate"
            },
            {
                "type": "3",
                "name": "Array3x"
            },
            {
                "type": "0",
                "name": "Distance",
                "subType": "number"
            },
            {
                "type": "0",
                "name": "Normalized",
                "subType": "boolean"
            }
        ],
        "portsOut": [
            {
                "type": "1",
                "name": "Next"
            },
            {
                "type": "0",
                "name": "X",
                "subType": "number"
            },
            {
                "type": "0",
                "name": "Y",
                "subType": "number"
            },
            {
                "type": "0",
                "name": "Z",
                "subType": "number"
            },
            {
                "type": "0",
                "name": "Spline Length",
                "subType": "number"
            }
        ],
        "name": "Ops.Array.Array3xSplinePositionAtDistance"
    },
    "summary": "get position in array3x/spline at distance from start",
    "docs": {
        "ports": [
            {
                "name": "Normalized",
                "text": "if true distance input is in the range 0-1"
            }
        ]
    },
    "youtubeid": "",
    "collections": [
        "pointArrays"
    ],
    "relatedops": null,
    "changelog": [
        {
            "message": "Ops.Array.Array3xSplinePositionAtDistance renamed to Ops.Array.SplinePositionAtDistanceArray3",
            "author": "pandur",
            "date": 1560415583904
        }
    ]
}
