{
    "id": "0a349745-20c8-44c4-8a70-214c7ccf87e9",
    "changelog": [
        {
            "message": "created op",
            "author": "pandur",
            "date": 1593869457023,
            "type": "new"
        },
        {
            "message": "Better handling of data URLs/file URLs/simple filenames",
            "type": "improvement",
            "author": "pandur",
            "date": 1757578403078
        },
        {
            "message": "Add suffixes for data URLs with mimetype",
            "type": "improvement",
            "author": "pandur",
            "date": 1757578451440
        }
    ],
    "authorName": "pandur",
    "created": 1593869652925,
    "layout": {
        "portsIn": [
            {
                "type": 5,
                "name": "URL"
            }
        ],
        "portsOut": [
            {
                "type": 5,
                "name": "Protocol"
            },
            {
                "type": 5,
                "name": "Host"
            },
            {
                "type": 5,
                "name": "Full Path"
            },
            {
                "type": 5,
                "name": "Filename"
            },
            {
                "type": 5,
                "name": "basename"
            },
            {
                "type": 5,
                "name": "Suffix"
            },
            {
                "type": 5,
                "name": "Is URL"
            },
            {
                "type": 5,
                "name": "queryParams"
            }
        ]
    },
    "summary": "information about a filename, like url protocol, suffix etc",
    "docs": {
        "ports": []
    },
    "license": "MIT",
    "exampleProjectId": "RyrLMg"
}
