{
    "summary": "use position and play pause state of cables timeline",
    "authorName": "pandur",
    "id": "53cb7b1a-56c7-405f-b427-12db78fbfd2f",
    "created": 1519814509715,
    "layout": {
        "portsIn": [],
        "portsOut": [
            {
                "type": 0,
                "name": "Play/Stop",
                "subType": "number"
            },
            {
                "type": 0,
                "name": "time",
                "subType": "number"
            }
        ]
    }
}
