{
    "layout": {
        "portsIn": [
            {
                "type": "0",
                "name": "number1",
                "subType": "number"
            }
        ],
        "portsOut": [
            {
                "type": "0",
                "name": "result",
                "subType": "number"
            }
        ],
        "name": "Ops.Math.Compare.IsEven"
    },
    "summary": "Checks if Value is even or not",
    "author": "55d744634cdc152216eb9aad",
    "authorName": "pandur",
    "id": "f462c64a-3e17-4de8-a77d-6735725fc9cc",
    "created": 1511163194086,
    "docs": {
        "ports": [
            {
                "name": "number1",
                "text": "The number you want to check"
            },
            {
                "name": "result",
                "text": "`true` if `Number` is even, `false` otherwise."
            }
        ]
    }
}
