{
    "authorName": "pandur",
    "id": "98d1c79e-71ea-468b-81fc-17da2cd3da89",
    "created": 1519837569086,
    "layout": {
        "portsIn": [
            {
                "type": "1",
                "name": "trigger"
            },
            {
                "type": "0",
                "name": "value",
                "subType": "number"
            },
            {
                "type": "0",
                "name": "index",
                "subType": "integer"
            },
            {
                "type": "1",
                "name": "reset"
            },
            {
                "type": "0",
                "name": "Show Min/Max",
                "subType": "boolean"
            },
            {
                "type": "0",
                "name": "Color Random Seed",
                "subType": "number"
            },
            {
                "type": "0",
                "name": "Texture Width",
                "subType": "integer"
            },
            {
                "type": "0",
                "name": "Texture Height",
                "subType": "integer"
            }
        ],
        "portsOut": [
            {
                "type": "2",
                "name": "Texture"
            }
        ],
        "name": "Ops.Gl.Textures.Graph"
    },
    "summary": "draw a graph of a value into a texture",
    "docs": {
        "ports": []
    }
}
