{
    "layout": {
        "portsIn": [
            {
                "type": "1",
                "name": "render"
            },
            {
                "type": "2",
                "name": "Geometry"
            },
            {
                "type": "0",
                "name": "Update All",
                "subType": "boolean"
            },
            {
                "type": "0",
                "name": "Update Face Indices",
                "subType": "boolean"
            },
            {
                "type": "0",
                "name": "Update Vertices",
                "subType": "boolean"
            },
            {
                "type": "0",
                "name": "Update Texcoords",
                "subType": "boolean"
            },
            {
                "type": "0",
                "name": "Vertex Numbers",
                "subType": "boolean"
            }
        ],
        "portsOut": [
            {
                "type": "1",
                "name": "trigger"
            }
        ],
        "name": "Ops.Gl.RenderGeometry"
    },
    "summary": "Render a geometry as mesh",
    "author": "55d744634cdc152216eb9aad",
    "authorName": "pandur",
    "id": "40fa6f13-ee0e-4386-a86b-711e1fbcf1bc",
    "created": 1509725147147,
    "docs": {
        "ports": []
    }
}
