{
    "updated": 1523364142190,
    "author": "55d744634cdc152216eb9aad",
    "authorName": "pandur",
    "id": "ff0bdad4-12ae-4444-b273-edfeab443a62",
    "created": 1508235921200,
    "layout": {
        "portsIn": [
            {
                "type": "1",
                "name": "Start VR"
            }
        ],
        "portsOut": [
            {
                "type": "1",
                "name": "VR Mainloop"
            },
            {
                "type": "0",
                "name": "Supported"
            },
            {
                "type": "0",
                "name": "VR Display"
            }
        ],
        "name": "Ops.Gl.Vr.WebVr"
    }
}
