{
    "authorName": "tim",
    "id": "98e19e37-88ca-4c07-bed7-a050dac31e3a",
    "created": 1516706915825,
    "layout": {
        "portsIn": [
            {
                "type": "0",
                "name": "Enabled",
                "subType": "boolean"
            },
            {
                "type": "0",
                "name": "Min Scale",
                "subType": "number"
            },
            {
                "type": "0",
                "name": "Max Scale",
                "subType": "number"
            },
            {
                "type": "1",
                "name": "Reset Scale"
            }
        ],
        "portsOut": [
            {
                "type": "0",
                "name": "Scale",
                "subType": "number"
            },
            {
                "type": "2",
                "name": "Event Details"
            }
        ],
        "name": "Ops.Devices.Mobile.Pinch"
    },
    "libs": [
        "hammer.js"
    ],
    "summary": "detect two finger pinch gestures on touchscreens",
    "docs": {
        "ports": []
    }
}
