{
    "id": "87d78a59-c8d4-4269-a3f8-af273741aae4",
    "changelog": [
        {
            "message": "created op",
            "author": "pandur",
            "date": 1622527751528
        },
        {
            "message": "cloned op from Ops.User.pandur.sidebartabs",
            "author": "pandur",
            "date": 1622529549185
        },
        {
            "message": "Ops.User.pandur.SideBarStyle renamed to Ops.Sidebar.SideBarStyle",
            "author": "pandur",
            "date": 1622531294836
        },
        {
            "message": "react properly to disconnecting parent",
            "author": "stephan",
            "date": 1643888127921
        }
    ],
    "authorName": "pandur",
    "created": 1622529549185,
    "layout": {
        "portsIn": [
            {
                "type": 2,
                "name": "link"
            },
            {
                "type": 0,
                "name": "Width",
                "subType": "integer"
            },
            {
                "type": 0,
                "name": "Round Corners",
                "subType": "number"
            },
            {
                "type": 5,
                "name": "Special Color"
            }
        ],
        "portsOut": [
            {
                "type": 2,
                "name": "childs"
            }
        ]
    },
    "summary": "adjust appearance of sidebar",
    "issues": "",

    "youtubeids": [],
    "docs": {
        "ports": []
    },
    "exampleProjectId": "o1fXgI"
}
