{
    "id": "9e74b275-a1ed-4d10-aba4-4b3311363a99",
    "changelog": [
        {
            "message": "created op",
            "author": "pandur",
            "date": 1590486860242,
            "type": "new"
        }
    ],
    "authorName": "pandur",
    "created": 1590486864887,
    "layout": {
        "portsIn": [
            {
                "type": 5,
                "name": "URL",
                "group": "Attributes"
            },
            {
                "type": 5,
                "name": "ID",
                "group": "Attributes"
            },
            {
                "type": 0,
                "name": "Active",
                "subType": "boolean"
            },
            {
                "type": 5,
                "name": "Style"
            }
        ],
        "portsOut": [
            {
                "type": 2,
                "name": "Element"
            }
        ]
    },
    "summary": "Show another website in an iframe element",
    "issues": "",
    "youtubeids": [],
    "docs": {
        "ports": [
            {
                "name": "URL",
                "text": "URL to load into the iFrame"
            },
            {
                "name": "ID",
                "text": "Unique CSS ID"
            },
            {
                "name": "Active",
                "text": "Active and render on screen"
            },
            {
                "name": "Style",
                "text": "Open built in editor to define the CSS style"
            },
            {
                "name": "Element",
                "text": "Element out"
            }
        ]
    },
    "exampleProjectId": "SLesr2",
    "license": "MIT"
}
