{
    "updated": 1515973257396,
    "authorName": "pandur",
    "id": "56b58d18-ef35-4ebd-80d6-8022a844adc0",
    "created": 1515969066808,
    "layout": {
        "portsIn": [
            {
                "type": "1",
                "name": "render"
            },
            {
                "type": "0",
                "name": "x"
            },
            {
                "type": "0",
                "name": "y"
            },
            {
                "type": "0",
                "name": "z"
            },
            {
                "type": "0",
                "name": "skip"
            },
            {
                "type": "0",
                "name": "num points"
            },
            {
                "type": "0",
                "name": "mul x"
            },
            {
                "type": "0",
                "name": "mul y"
            },
            {
                "type": "0",
                "name": "mul z"
            }
        ],
        "portsOut": [
            {
                "type": "1",
                "name": "trigger"
            }
        ],
        "name": "Ops.Gl.Matrix.LissajousTransform"
    }
}
