{
    "updated": 1511782490566,
    "author": "55d744634cdc152216eb9aad",
    "authorName": "pandur",
    "id": "d01a0ac2-a457-416a-8a45-7db92fb46316",
    "created": 1511782368102,
    "layout": {
        "portsIn": [
            {
                "type": "1",
                "name": "render"
            }
        ],
        "portsOut": [
            {
                "type": "1",
                "name": "trigger"
            }
        ],
        "name": "Ops.Gl.Shader.ShowTexCoordsMaterial"
    },
    "summary": "visualize texturecoordinates of a mesh "
}
