{
    "authorName": "pandur",
    "id": "9892b737-099d-4b33-8789-0ab9bdc40dab",
    "created": 1519812832119,
    "layout": {
        "portsIn": [
            {
                "type": "1",
                "name": "render"
            },
            {
                "type": "0",
                "name": "density",
                "subType": "number"
            },
            {
                "type": "2",
                "name": "depth texture"
            },
            {
                "type": "0",
                "name": "ignore infinity",
                "subType": "boolean"
            },
            {
                "type": "0",
                "name": "fog r",
                "subType": "number"
            },
            {
                "type": "0",
                "name": "fog g",
                "subType": "number"
            },
            {
                "type": "0",
                "name": "fog b",
                "subType": "number"
            },
            {
                "type": "0",
                "name": "fog a",
                "subType": "number"
            },
            {
                "type": "0",
                "name": "start",
                "subType": "number"
            }
        ],
        "portsOut": [
            {
                "type": "1",
                "name": "trigger"
            }
        ],
        "name": "Ops.Gl.TextureEffects.Fog"
    },
    "summary": "objects further away are colored to enhance the perception of distance.",
    "docs": {
        "ports": []
    }
}
